markovpack/commands/__init__.py
markovpack/commands/markov.py
markovpack/events/__init__.py
markovpack/stars/__init__.py
markovpack/tables/__init__.py
markovpack/version.py
markovpack-0.3.2.dist-info/LICENSE.txt
markovpack-0.3.2.dist-info/WHEEL
markovpack-0.3.2.dist-info/METADATA
markovpack-0.3.2.dist-info/RECORD
