Metadata-Version: 2.1
Name: markovpack
Version: 0.3.2
Summary: A Royalnet pack to have fun with Markovify.
Home-page: https://github.com/Steffo99/markovpack
Author: Stefano Pigozzi
Author-email: ste.pigozzi@gmail.com
Requires-Python: >=3.8,<4.0
Classifier: Development Status :: 4 - Beta
Classifier: License :: OSI Approved :: GNU Affero General Public License v3 or later (AGPLv3+)
Classifier: Operating System :: OS Independent
Classifier: Programming Language :: Python :: 3
Classifier: Programming Language :: Python :: 3.8
Requires-Dist: markovify (>=0.8.0,<0.9.0)
Requires-Dist: royalnet[telegram,discord,alchemy_easy,bard,constellation,sentry,herald,coloredlogs,matrix] (>=5.9.2,<6.0.0)
